jax2d/__init__.py
jax2d/collision.py
jax2d/engine.py
jax2d/joint.py
jax2d/maths.py
jax2d/scene.py
jax2d/sim_state.py
jax2d-1.0.1.dist-info/LICENSE
jax2d-1.0.1.dist-info/METADATA
jax2d-1.0.1.dist-info/WHEEL
jax2d-1.0.1.dist-info/top_level.txt
jax2d-1.0.1.dist-info/RECORD
