Metadata-Version: 2.2
Name: jax2d
Version: 1.0.1
Summary: A JAX 2D Rigid-Body Physics Engine
Author-email: Michael Matthews <michael.matthews@eng.ox.ac.uk>, Michael Beukman <michael.beukman@eng.ox.ac.uk>
Project-URL: Homepage, https://github.com/MichaelTMatthews/Jax2D
Project-URL: Issues, https://github.com/MichaelTMatthews/Jax2D/Issues
Classifier: Programming Language :: Python :: 3
Classifier: License :: OSI Approved :: MIT License
Classifier: Operating System :: OS Independent
Requires-Python: >=3.10
License-File: LICENSE
Requires-Dist: jax
Requires-Dist: flax
Provides-Extra: dev
Requires-Dist: black; extra == "dev"
Requires-Dist: pre-commit; extra == "dev"
Requires-Dist: jaxgl; extra == "dev"
Requires-Dist: pygame; extra == "dev"
